colour/__init__.py
colour/colour.py
colouralpha-0.1.6.dist-info/LICENSE
colouralpha-0.1.6.dist-info/LICENSE.old
colouralpha-0.1.6.dist-info/WHEEL
colouralpha-0.1.6.dist-info/METADATA
colouralpha-0.1.6.dist-info/RECORD
