Metadata-Version: 2.1
Name: colouralpha
Version: 0.1.6
Summary: Python color representations manipulation library (RGB, HSL, web, ...)
License: BSD-3-Clause
Author: Marcin Serwin
Author-email: marcin.serwin0@protonmail.com
Requires-Python: >=3.7,<4.0
Classifier: License :: OSI Approved :: BSD License
Classifier: Programming Language :: Python :: 3
Classifier: Programming Language :: Python :: 3.10
Classifier: Programming Language :: Python :: 3.7
Classifier: Programming Language :: Python :: 3.8
Classifier: Programming Language :: Python :: 3.9
